SynCDsGen/__init__.py
SynCDsGen/syncdsgen.py
syncdsgen-0.0.17.dist-info/METADATA
syncdsgen-0.0.17.dist-info/WHEEL
syncdsgen-0.0.17.dist-info/licenses/LICENCE
syncdsgen-0.0.17.dist-info/RECORD
