Metadata-Version: 2.1
Name: syncdsgen
Version: 0.0.17
Summary: A package to generate synthetic coding sequences data
Project-URL: Homepage, https://github.com/wl-research/syncdsgen
Author-email: Ramses TANANKEM <tanankemr@gmail.com>
License-File: LICENCE
Classifier: License :: OSI Approved :: MIT License
Classifier: Operating System :: OS Independent
Classifier: Programming Language :: Python :: 3
Requires-Python: >=3.7
Requires-Dist: numpy
Requires-Dist: pandas
Requires-Dist: pyro-ppl
Requires-Dist: torch
